LobbyBot/__init__.py
LobbyBot-8.0.3.dist-info/METADATA
LobbyBot-8.0.3.dist-info/WHEEL
LobbyBot-8.0.3.dist-info/top_level.txt
LobbyBot-8.0.3.dist-info/RECORD
