Metadata-Version: 2.1
Name: LobbyBot
Version: 8.0.3
Summary: 24/7 Fortnite Lobbybot With Admin Controls
Home-page: https://github.com/PirxcyFinal/pirxcybotv4
Author: Pirxcy
Classifier: Programming Language :: Python :: 3
Classifier: License :: OSI Approved :: MIT License
Classifier: Operating System :: OS Independent
Requires-Dist: sanic (==21.6.2)
Requires-Dist: fortnitepy
Requires-Dist: aiohttp
Requires-Dist: crayons
Requires-Dist: psutil
Requires-Dist: PirxcyPinger
